dicto/__init__.py
dicto/api.py
dicto-0.2.0.dist-info/LICENSE
dicto-0.2.0.dist-info/WHEEL
dicto-0.2.0.dist-info/METADATA
dicto-0.2.0.dist-info/RECORD
