Metadata-Version: 2.1
Name: dicto
Version: 0.2.0
Summary: 
Home-page: https://cgarciae.github.io/dicto
License: MIT
Author: Cristian Garcia
Author-email: cgarcia.e88@gmail.com
Requires-Python: >=3.7,<4.0
Classifier: License :: OSI Approved :: MIT License
Classifier: Programming Language :: Python :: 3
Classifier: Programming Language :: Python :: 3.7
Classifier: Programming Language :: Python :: 3.8
Requires-Dist: pyyaml (>=5.3,<6.0)
Requires-Dist: xmltodict (>=0.12.0,<0.13.0)
Project-URL: Repository, https://github.com/cgarciae/dicto
